select_ai/__init__.py
select_ai/_abc.py
select_ai/_enums.py
select_ai/_validations.py
select_ai/action.py
select_ai/async_profile.py
select_ai/base_profile.py
select_ai/conversation.py
select_ai/credential.py
select_ai/db.py
select_ai/errors.py
select_ai/feedback.py
select_ai/privilege.py
select_ai/profile.py
select_ai/provider.py
select_ai/sql.py
select_ai/summary.py
select_ai/synthetic_data.py
select_ai/vector_index.py
select_ai/version.py
select_ai/agent/__init__.py
select_ai/agent/core.py
select_ai/agent/sql.py
select_ai/agent/task.py
select_ai/agent/team.py
select_ai/agent/tool.py
select_ai-1.2.2.dist-info/licenses/LICENSE.txt
select_ai-1.2.2.dist-info/METADATA
select_ai-1.2.2.dist-info/WHEEL
select_ai-1.2.2.dist-info/top_level.txt
select_ai-1.2.2.dist-info/RECORD
