Metadata-Version: 2.4
Name: select_ai
Version: 1.2.2
Summary: Select AI for Python
Author-email: Abhishek Singh <abhishek.o.singh@oracle.com>
Maintainer-email: Abhishek Singh <abhishek.o.singh@oracle.com>
License-Expression: UPL-1.0
Project-URL: Homepage, https://github.com/oracle/python-select-ai
Project-URL: Repository, https://github.com/oracle/python-select-ai
Project-URL: Issues, https://github.com/oracle/python-select-ai/issues
Project-URL: Documentation, https://oracle.github.io/python-select-ai/
Keywords: oracle,select-ai,adbs,autonomous database serverless
Classifier: Development Status :: 5 - Production/Stable
Classifier: Intended Audience :: Developers
Classifier: Natural Language :: English
Classifier: Operating System :: OS Independent
Classifier: Programming Language :: Python :: 3 :: Only
Classifier: Programming Language :: Python :: 3.9
Classifier: Programming Language :: Python :: 3.10
Classifier: Programming Language :: Python :: 3.11
Classifier: Programming Language :: Python :: 3.12
Classifier: Programming Language :: Python :: 3.13
Classifier: Programming Language :: Python :: 3.14
Classifier: Programming Language :: Python :: Implementation :: CPython
Classifier: Topic :: Database
Classifier: Topic :: Scientific/Engineering :: Artificial Intelligence
Classifier: Topic :: Software Development :: Libraries :: Python Modules
Requires-Python: >=3.9
License-File: LICENSE.txt
Requires-Dist: oracledb
Requires-Dist: pandas==2.2.3
Provides-Extra: test
Requires-Dist: anyio; extra == "test"
Requires-Dist: pytest; extra == "test"
Dynamic: license-file
